ws2812b_controller.v



module NEOPIX
#(parameter num_pixels = 3,
T0H = 6,
T0L = 14,
T1H = 13,
T1L = 7,
RES = 880
)
(
  input  wire clk,
  input  wire [71:0] pixel_data,
  output reg out);


//0->1023
reg [9:0] timer;
reg [5:0] bit_pointer;
reg [$clog2(num_pixels):0] pixel_pointer;

initial begin
	timer = 0;
	bit_pointer = 0;
	pixel_pointer = 0;
end


//T0P and T1P are equal now, but they might not be on all systems
//T0 period
localparam T0_period = T0H + T0L;
//T1 period
localparam T1_period = T1H + T1L;


/*
this always block drives:
	timer,
	bit_pointer,
	out,
	pixel_pointer
*/
always @ (posedge clk) begin


//$display("bit_pointer: %d, timer: %d, data: %d", bit_pointer, timer, PIX_DAT[pointer]);




if(pixel_pointer < num_pixels) begin

	timer <= timer + 1;

	if(pixel_data[pixel_pointer * 24 + 23 - bit_pointer] == 1) begin
		//transmit 1
		
		
		if(timer < T1H) 	out <= 1;
		else				out <= 0;

		if(timer == T1_period - 1) begin
			$display("transmitted 1 %0t",$time); 
			timer 				<= 0;

			if(bit_pointer + 1 > 23)begin
				$display("pixel pointer increment %0t",$time); 
				pixel_pointer 			<= pixel_pointer + 1;
				bit_pointer 			<= 0;
			end else begin
				$display("bit pointer increment %0t",$time); 
				bit_pointer 		<= bit_pointer + 1;
			end

		end else begin

		end


	end else begin
		//transmit 0
		

		if(timer < T0H) 	out <= 1;
		else				out <= 0;
		
		if(timer == T0_period - 1) begin
			$display("transmitted 0 %0t",$time); 
			timer 				<= 0;
			

			if(bit_pointer + 1 > 23)begin
				$display("pixel pointer increment %0t",$time); 
				pixel_pointer 			<= pixel_pointer + 1;
				bit_pointer 			<= 0;
			end else begin
				$display("bit pointer increment %0t",$time); 
				bit_pointer 		<= bit_pointer + 1;
			end

				

		end else begin

		end

	end

	if(bit_pointer > 23) begin 
		$display("reset pixel pointer %0t",$time); 
		bit_pointer 			<= 0;
		pixel_pointer 			<= pixel_pointer + 1;
	end


end else begin
	//res pulse

	$display("reset %0t",$time); 

	if(timer <= RES) begin
		timer					<= timer + 1;
		pixel_pointer 			<= pixel_pointer;
	end else begin
		timer 					<= 0;
		pixel_pointer 			<= 0;
	end

	out 						<= 0;
	bit_pointer 				<= 0;

end





end

endmodule


/*
0 code:
/T0H\_T0L_

1 code:
/T1H\_T1L_

RET code
_Treset_

name		timing [us]		timing	[ns]		# of clock pulse		ideal choice			error
				
T0H			0.4  [us]		400		[ns]		5	->	8				6						+-150 [ns]
T1H			0.8  [us]		800		[ns]		11	->	15				13						+-150 [ns]
T0L			0.85 [us]		850		[ns]		12	->	15				14						+-150 [ns]
T1L			0.45 [us]		450		[ns]		5	->	9				7						+-150 [ns]
RES			t>50 [us]		50_000	[ns]		800						810

note: 50_000 / 62.5 = 800
	must be LONGER than 50_000 ns

16Mhz clock is
62.5ns


conclusion:
	T0H and T1L can be the same
	T1H and T0L can be the same

	T0H = T1L =  6 * 62.5 [ns] = 375   [ns]
	T1H = T0L = 13 * 62.5 [ns] = 812.5 [ns]


*/

//4   time ticks for 0.4us
//2  time ticks for 0.85us
//800 time ticks for 50us

SIM/pixel TB.sv
`timescale 1ns/1ns
module neopixel_TB();

logic clk;

reg [7:0] R, G, B;
logic out;

NEOPIX neo(clk, {B, R, G}, out);

always #31.25 clk = !clk;


initial begin

$dumpfile("waves.vcd");
$dumpvars;

clk = 0;

R = 8'b10101010;
G = 8'b10101010;
B = 8'b10101010;

#10;

#500;

end




endmodule

SIM/waves.vcd
$date
	Thu Nov 10 20:16:29 2022
$end
$version
	ModelSim Version 2020.1
$end
$timescale
	1ns
$end

$scope module neopixel_TB $end
$var reg 1 ! clk $end
$var reg 8 " R [7:0] $end
$var reg 8 # G [7:0] $end
$var reg 8 $ B [7:0] $end
$var reg 1 % out $end

$scope module neo $end
$var parameter 32 & num_pixels $end
$var parameter 32 ' T0H $end
$var parameter 32 ( T0L $end
$var parameter 32 ) T1H $end
$var parameter 32 * T1L $end
$var parameter 32 + RES $end
$var parameter 32 , T0_period $end
$var parameter 32 - T1_period $end
$var wire 1 . clk $end
$var wire 1 / pixel_data [23] $end
$var wire 1 0 pixel_data [22] $end
$var wire 1 1 pixel_data [21] $end
$var wire 1 2 pixel_data [20] $end
$var wire 1 3 pixel_data [19] $end
$var wire 1 4 pixel_data [18] $end
$var wire 1 5 pixel_data [17] $end
$var wire 1 6 pixel_data [16] $end
$var wire 1 7 pixel_data [15] $end
$var wire 1 8 pixel_data [14] $end
$var wire 1 9 pixel_data [13] $end
$var wire 1 : pixel_data [12] $end
$var wire 1 ; pixel_data [11] $end
$var wire 1 < pixel_data [10] $end
$var wire 1 = pixel_data [9] $end
$var wire 1 > pixel_data [8] $end
$var wire 1 ? pixel_data [7] $end
$var wire 1 @ pixel_data [6] $end
$var wire 1 A pixel_data [5] $end
$var wire 1 B pixel_data [4] $end
$var wire 1 C pixel_data [3] $end
$var wire 1 D pixel_data [2] $end
$var wire 1 E pixel_data [1] $end
$var wire 1 F pixel_data [0] $end
$var reg 1 G out $end
$var reg 10 H timer [9:0] $end
$var reg 6 I bit_pointer [5:0] $end
$var reg 2 J pixel_pointer [1:0] $end
$upscope $end
$upscope $end

$scope begin std $end
$upscope $end
$enddefinitions $end
#0
$dumpvars
0!
b10101010 "
b10101010 #
b10101010 $
x%
xG
b0 H
b0 I
b0 J
b10 &
b110 '
b1110 (
b1101 )
b111 *
b1100101010 +
b10100 ,
b10100 -
0.
0F
1E
0D
1C
0B
1A
0@
1?
0>
1=
0<
1;
0:
19
08
17
06
15
04
13
02
11
00
1/
$end
#31
1!
1.
b1 H
1G
1%
#62
0!
0.
#93
1!
1.
b10 H
#124
0!
0.
#155
1!
1.
b11 H
#186
0!
0.
#217
1!
1.
b100 H
#248
0!
0.
#279
1!
1.
b101 H
#310
0!
0.
#341
1!
1.
b110 H
#372
0!
0.
#403
1!
1.
b111 H
#434
0!
0.
#465
1!
1.
b1000 H
#496
0!
0.
#527
1!
1.
b1001 H
#558
0!
0.
#589
1!
1.
b1010 H
#620
0!
0.
#651
1!
1.
b1011 H
#682
0!
0.
#713
1!
1.
b1100 H
#744
0!
0.
#775
1!
1.
b1101 H
#806
0!
0.
#837
1!
1.
b1110 H
0G
0%
#868
0!
0.
#899
1!
1.
b1111 H
#930
0!
0.
#961
1!
1.
b10000 H
#992
0!
0.
#1023
1!
1.
b10001 H
#1054
0!
0.
#1085
1!
1.
b10010 H
#1116
0!
0.
#1147
1!
1.
b10011 H
#1178
0!
0.
#1209
1!
1.
b10100 H
b0 H
b1 I
#1240
0!
0.
#1271
1!
1.
b1 H
1G
1%
#1302
0!
0.
#1333
1!
1.
b10 H
#1364
0!
0.
#1395
1!
1.
b11 H
#1426
0!
0.
#1457
1!
1.
b100 H
#1488
0!
0.
#1519
1!
1.
b101 H
#1550
0!
0.
#1581
1!
1.
b110 H
#1612
0!
0.
#1643
1!
1.
b111 H
0G
0%
#1674
0!
0.
#1705
1!
1.
b1000 H
#1736
0!
0.
#1767
1!
1.
b1001 H
#1798
0!
0.
#1829
1!
1.
b1010 H
#1860
0!
0.
#1891
1!
1.
b1011 H
#1922
0!
0.
#1953
1!
1.
b1100 H
#1984
0!
0.
#2015
1!
1.
b1101 H
#2046
0!
0.
#2077
1!
1.
b1110 H
#2108
0!
0.
#2139
1!
1.
b1111 H
#2170
0!
0.
#2201
1!
1.
b10000 H
#2232
0!
0.
#2263
1!
1.
b10001 H
#2294
0!
0.
#2325
1!
1.
b10010 H
#2356
0!
0.
#2387
1!
1.
b10011 H
#2418
0!
0.
#2449
1!
1.
b10100 H
b0 H
b10 I
#2480
0!
0.
#2511
1!
1.
b1 H
1G
1%
#2542
0!
0.
#2573
1!
1.
b10 H
#2604
0!
0.
#2635
1!
1.
b11 H
#2666
0!
0.
#2697
1!
1.
b100 H
#2728
0!
0.
#2759
1!
1.
b101 H
#2790
0!
0.
#2821
1!
1.
b110 H
#2852
0!
0.
#2883
1!
1.
b111 H
#2914
0!
0.
#2945
1!
1.
b1000 H
#2976
0!
0.
#3007
1!
1.
b1001 H
#3038
0!
0.
#3069
1!
1.
b1010 H
#3100
0!
0.
#3131
1!
1.
b1011 H
#3162
0!
0.
#3193
1!
1.
b1100 H
#3224
0!
0.
#3255
1!
1.
b1101 H
#3286
0!
0.
#3317
1!
1.
b1110 H
0G
0%
#3348
0!
0.
#3379
1!
1.
b1111 H
#3410
0!
0.
#3441
1!
1.
b10000 H
#3472
0!
0.
#3503
1!
1.
b10001 H
#3534
0!
0.
#3565
1!
1.
b10010 H
#3596
0!
0.
#3627
1!
1.
b10011 H
#3658
0!
0.
#3689
1!
1.
b10100 H
b0 H
b11 I
#3720
0!
0.
#3751
1!
1.
b1 H
1G
1%
#3782
0!
0.
#3813
1!
1.
b10 H
#3844
0!
0.
#3875
1!
1.
b11 H
#3906
0!
0.
#3937
1!
1.
b100 H
#3968
0!
0.
#3999
1!
1.
b101 H
#4030
0!
0.
#4061
1!
1.
b110 H
#4092
0!
0.
#4123
1!
1.
b111 H
0G
0%
#4154
0!
0.
#4185
1!
1.
b1000 H
#4216
0!
0.
#4247
1!
1.
b1001 H
#4278
0!
0.
#4309
1!
1.
b1010 H
#4340
0!
0.
#4371
1!
1.
b1011 H
#4402
0!
0.
#4433
1!
1.
b1100 H
#4464
0!
0.
#4495
1!
1.
b1101 H
#4526
0!
0.
#4557
1!
1.
b1110 H
#4588
0!
0.
#4619
1!
1.
b1111 H
#4650
0!
0.
#4681
1!
1.
b10000 H
#4712
0!
0.
#4743
1!
1.
b10001 H
#4774
0!
0.
#4805
1!
1.
b10010 H
#4836
0!
0.
#4867
1!
1.
b10011 H
#4898
0!
0.
#4929
1!
1.
b10100 H
b0 H
b100 I
#4960
0!
0.
#4991
1!
1.
b1 H
1G
1%
#5022
0!
0.
#5053
1!
1.
b10 H
#5084
0!
0.
#5115
1!
1.
b11 H
#5146
0!
0.
#5177
1!
1.
b100 H
#5208
0!
0.
#5239
1!
1.
b101 H
#5270
0!
0.
#5301
1!
1.
b110 H
#5332
0!
0.
#5363
1!
1.
b111 H
#5394
0!
0.
#5425
1!
1.
b1000 H
#5456
0!
0.
#5487
1!
1.
b1001 H
#5518
0!
0.
#5549
1!
1.
b1010 H
#5580
0!
0.
#5611
1!
1.
b1011 H
#5642
0!
0.
#5673
1!
1.
b1100 H
#5704
0!
0.
#5735
1!
1.
b1101 H
#5766
0!
0.
#5797
1!
1.
b1110 H
0G
0%
#5828
0!
0.
#5859
1!
1.
b1111 H
#5890
0!
0.
#5921
1!
1.
b10000 H
#5952
0!
0.
#5983
1!
1.
b10001 H
#6014
0!
0.
#6045
1!
1.
b10010 H
#6076
0!
0.
#6107
1!
1.
b10011 H
#6138
0!
0.
#6169
1!
1.
b10100 H
b0 H
b101 I
#6200
0!
0.
#6231
1!
1.
b1 H
1G
1%
#6262
0!
0.
#6293
1!
1.
b10 H
#6324
0!
0.
#6355
1!
1.
b11 H
#6386
0!
0.
#6417
1!
1.
b100 H
#6448
0!
0.
#6479
1!
1.
b101 H
#6510
0!
0.
#6541
1!
1.
b110 H
#6572
0!
0.
#6603
1!
1.
b111 H
0G
0%
#6634
0!
0.
#6665
1!
1.
b1000 H
#6696
0!
0.
#6727
1!
1.
b1001 H
#6758
0!
0.
#6789
1!
1.
b1010 H
#6820
0!
0.
#6851
1!
1.
b1011 H
#6882
0!
0.
#6913
1!
1.
b1100 H
#6944
0!
0.
#6975
1!
1.
b1101 H
#7006
0!
0.
#7037
1!
1.
b1110 H
#7068
0!
0.
#7099
1!
1.
b1111 H
#7130
0!
0.
#7161
1!
1.
b10000 H
#7192
0!
0.
#7223
1!
1.
b10001 H
#7254
0!
0.
#7285
1!
1.
b10010 H
#7316
0!
0.
#7347
1!
1.
b10011 H
#7378
0!
0.
#7409
1!
1.
b10100 H
b0 H
b110 I
#7440
0!
0.
#7471
1!
1.
b1 H
1G
1%
#7502
0!
0.
#7533
1!
1.
b10 H
#7564
0!
0.
#7595
1!
1.
b11 H
#7626
0!
0.
#7657
1!
1.
b100 H
#7688
0!
0.
#7719
1!
1.
b101 H
#7750
0!
0.
#7781
1!
1.
b110 H
#7812
0!
0.
#7843
1!
1.
b111 H
#7874
0!
0.
#7905
1!
1.
b1000 H
#7936
0!
0.
#7967
1!
1.
b1001 H
#7998
0!
0.
#8029
1!
1.
b1010 H
#8060
0!
0.
#8091
1!
1.
b1011 H
#8122
0!
0.
#8153
1!
1.
b1100 H
#8184
0!
0.
#8215
1!
1.
b1101 H
#8246
0!
0.
#8277
1!
1.
b1110 H
0G
0%
#8308
0!
0.
#8339
1!
1.
b1111 H
#8370
0!
0.
#8401
1!
1.
b10000 H
#8432
0!
0.
#8463
1!
1.
b10001 H
#8494
0!
0.
#8525
1!
1.
b10010 H
#8556
0!
0.
#8587
1!
1.
b10011 H
#8618
0!
0.
#8649
1!
1.
b10100 H
b0 H
b111 I
#8680
0!
0.
#8711
1!
1.
b1 H
1G
1%
#8742
0!
0.
#8773
1!
1.
b10 H
#8804
0!
0.
#8835
1!
1.
b11 H
#8866
0!
0.
#8897
1!
1.
b100 H
#8928
0!
0.
#8959
1!
1.
b101 H
#8990
0!
0.
#9021
1!
1.
b110 H
#9052
0!
0.
#9083
1!
1.
b111 H
0G
0%
#9114
0!
0.
#9145
1!
1.
b1000 H
#9176
0!
0.
#9207
1!
1.
b1001 H
#9238
0!
0.
#9269
1!
1.
b1010 H
#9300
0!
0.
#9331
1!
1.
b1011 H
#9362
0!
0.
#9393
1!
1.
b1100 H
#9424
0!
0.
#9455
1!
1.
b1101 H
#9486
0!
0.
#9517
1!
1.
b1110 H
#9548
0!
0.
#9579
1!
1.
b1111 H
#9610
0!
0.
#9641
1!
1.
b10000 H
#9672
0!
0.
#9703
1!
1.
b10001 H
#9734
0!
0.
#9765
1!
1.
b10010 H
#9796
0!
0.
#9827
1!
1.
b10011 H
#9858
0!
0.
#9889
1!
1.
b10100 H
b0 H
b1000 I
#9920
0!
0.
#9951
1!
1.
b1 H
1G
1%
#9982
0!
0.
#10013
1!
1.
b10 H
#10044
0!
0.
#10075
1!
1.
b11 H
#10106
0!
0.
#10137
1!
1.
b100 H
#10168
0!
0.
#10199
1!
1.
b101 H
#10230
0!
0.
#10261
1!
1.
b110 H
#10292
0!
0.
#10323
1!
1.
b111 H
#10354
0!
0.
#10385
1!
1.
b1000 H
#10416
0!
0.
#10447
1!
1.
b1001 H
#10478
0!
0.
#10509
1!
1.
b1010 H
#10540
0!
0.
#10571
1!
1.
b1011 H
#10602
0!
0.
#10633
1!
1.
b1100 H
#10664
0!
0.
#10695
1!
1.
b1101 H
#10726
0!
0.
#10757
1!
1.
b1110 H
0G
0%
#10788
0!
0.
#10819
1!
1.
b1111 H
#10850
0!
0.
#10881
1!
1.
b10000 H
#10912
0!
0.
#10943
1!
1.
b10001 H
#10974
0!
0.
#11005
1!
1.
b10010 H
#11036
0!
0.
#11067
1!
1.
b10011 H
#11098
0!
0.
#11129
1!
1.
b10100 H
b0 H
b1001 I
#11160
0!
0.
#11191
1!
1.
b1 H
1G
1%
#11222
0!
0.
#11253
1!
1.
b10 H
#11284
0!
0.
#11315
1!
1.
b11 H
#11346
0!
0.
#11377
1!
1.
b100 H
#11408
0!
0.
#11439
1!
1.
b101 H
#11470
0!
0.
#11501
1!
1.
b110 H
#11532
0!
0.
#11563
1!
1.
b111 H
0G
0%
#11594
0!
0.
#11625
1!
1.
b1000 H
#11656
0!
0.
#11687
1!
1.
b1001 H
#11718
0!
0.
#11749
1!
1.
b1010 H
#11780
0!
0.
#11811
1!
1.
b1011 H
#11842
0!
0.
#11873
1!
1.
b1100 H
#11904
0!
0.
#11935
1!
1.
b1101 H
#11966
0!
0.
#11997
1!
1.
b1110 H
#12028
0!
0.
#12059
1!
1.
b1111 H
#12090
0!
0.
#12121
1!
1.
b10000 H
#12152
0!
0.
#12183
1!
1.
b10001 H
#12214
0!
0.
#12245
1!
1.
b10010 H
#12276
0!
0.
#12307
1!
1.
b10011 H
#12338
0!
0.
#12369
1!
1.
b10100 H
b0 H
b1010 I
#12400
0!
0.
#12431
1!
1.
b1 H
1G
1%
#12462
0!
0.
#12493
1!
1.
b10 H
#12524
0!
0.
#12555
1!
1.
b11 H
#12586
0!
0.
#12617
1!
1.
b100 H
#12648
0!
0.
#12679
1!
1.
b101 H
#12710
0!
0.
#12741
1!
1.
b110 H
#12772
0!
0.
#12803
1!
1.
b111 H
#12834
0!
0.
#12865
1!
1.
b1000 H
#12896
0!
0.
#12927
1!
1.
b1001 H
#12958
0!
0.
#12989
1!
1.
b1010 H
#13020
0!
0.
#13051
1!
1.
b1011 H
#13082
0!
0.
#13113
1!
1.
b1100 H
#13144
0!
0.
#13175
1!
1.
b1101 H
#13206
0!
0.
#13237
1!
1.
b1110 H
0G
0%
#13268
0!
0.
#13299
1!
1.
b1111 H
#13330
0!
0.
#13361
1!
1.
b10000 H
#13392
0!
0.
#13423
1!
1.
b10001 H
#13454
0!
0.
#13485
1!
1.
b10010 H
#13516
0!
0.
#13547
1!
1.
b10011 H
#13578
0!
0.
#13609
1!
1.
b10100 H
b0 H
b1011 I
#13640
0!
0.
#13671
1!
1.
b1 H
1G
1%
#13702
0!
0.
#13733
1!
1.
b10 H
#13764
0!
0.
#13795
1!
1.
b11 H
#13826
0!
0.
#13857
1!
1.
b100 H
#13888
0!
0.
#13919
1!
1.
b101 H
#13950
0!
0.
#13981
1!
1.
b110 H
#14012
0!
0.
#14043
1!
1.
b111 H
0G
0%
#14074
0!
0.
#14105
1!
1.
b1000 H
#14136
0!
0.
#14167
1!
1.
b1001 H
#14198
0!
0.
#14229
1!
1.
b1010 H
#14260
0!
0.
#14291
1!
1.
b1011 H
#14322
0!
0.
#14353
1!
1.
b1100 H
#14384
0!
0.
#14415
1!
1.
b1101 H
#14446
0!
0.
#14477
1!
1.
b1110 H
#14508
0!
0.
#14539
1!
1.
b1111 H
#14570
0!
0.
#14601
1!
1.
b10000 H
#14632
0!
0.
#14663
1!
1.
b10001 H
#14694
0!
0.
#14725
1!
1.
b10010 H
#14756
0!
0.
#14787
1!
1.
b10011 H
#14818
0!
0.
#14849
1!
1.
b10100 H
b0 H
b1100 I
#14880
0!
0.
#14911
1!
1.
b1 H
1G
1%
#14942
0!
0.
#14973
1!
1.
b10 H
#15004
0!
0.
#15035
1!
1.
b11 H
#15066
0!
0.
#15097
1!
1.
b100 H
#15128
0!
0.
#15159
1!
1.
b101 H
#15190
0!
0.
#15221
1!
1.
b110 H
#15252
0!
0.
#15283
1!
1.
b111 H
#15314
0!
0.
#15345
1!
1.
b1000 H
#15376
0!
0.
#15407
1!
1.
b1001 H
#15438
0!
0.
#15469
1!
1.
b1010 H
#15500
0!
0.
#15531
1!
1.
b1011 H
#15562
0!
0.
#15593
1!
1.
b1100 H
#15624
0!
0.
#15655
1!
1.
b1101 H
#15686
0!
0.
#15717
1!
1.
b1110 H
0G
0%
#15748
0!
0.
#15779
1!
1.
b1111 H
#15810
0!
0.
#15841
1!
1.
b10000 H
#15872
0!
0.
#15903
1!
1.
b10001 H
#15934
0!
0.
#15965
1!
1.
b10010 H
#15996
0!
0.
#16027
1!
1.
b10011 H
#16058
0!
0.
#16089
1!
1.
b10100 H
b0 H
b1101 I
#16120
0!
0.
#16151
1!
1.
b1 H
1G
1%
#16182
0!
0.
#16213
1!
1.
b10 H
#16244
0!
0.
#16275
1!
1.
b11 H
#16306
0!
0.
#16337
1!
1.
b100 H
#16368
0!
0.
#16399
1!
1.
b101 H
#16430
0!
0.
#16461
1!
1.
b110 H
#16492
0!
0.
#16523
1!
1.
b111 H
0G
0%
#16554
0!
0.
#16585
1!
1.
b1000 H
#16616
0!
0.
#16647
1!
1.
b1001 H
#16678
0!
0.
#16709
1!
1.
b1010 H
#16740
0!
0.
#16771
1!
1.
b1011 H
#16802
0!
0.
#16833
1!
1.
b1100 H
#16864
0!
0.
#16895
1!
1.
b1101 H
#16926
0!
0.
#16957
1!
1.
b1110 H
#16988
0!
0.
#17019
1!
1.
b1111 H
#17050
0!
0.
#17081
1!
1.
b10000 H
#17112
0!
0.
#17143
1!
1.
b10001 H
#17174
0!
0.
#17205
1!
1.
b10010 H
#17236
0!
0.
#17267
1!
1.
b10011 H
#17298
0!
0.
#17329
1!
1.
b10100 H
b0 H
b1110 I
#17360
0!
0.
#17391
1!
1.
b1 H
1G
1%
#17422
0!
0.
#17453
1!
1.
b10 H
#17484
0!
0.
#17515
1!
1.
b11 H
#17546
0!
0.
#17577
1!
1.
b100 H
#17608
0!
0.
#17639
1!
1.
b101 H
#17670
0!
0.
#17701
1!
1.
b110 H
#17732
0!
0.
#17763
1!
1.
b111 H
#17794
0!
0.
#17825
1!
1.
b1000 H
#17856
0!
0.
#17887
1!
1.
b1001 H
#17918
0!
0.
#17949
1!
1.
b1010 H
#17980
0!
0.
#18011
1!
1.
b1011 H
#18042
0!
0.
#18073
1!
1.
b1100 H
#18104
0!
0.
#18135
1!
1.
b1101 H
#18166
0!
0.
#18197
1!
1.
b1110 H
0G
0%
#18228
0!
0.
#18259
1!
1.
b1111 H
#18290
0!
0.
#18321
1!
1.
b10000 H
#18352
0!
0.
#18383
1!
1.
b10001 H
#18414
0!
0.
#18445
1!
1.
b10010 H
#18476
0!
0.
#18507
1!
1.
b10011 H
#18538
0!
0.
#18569
1!
1.
b10100 H
b0 H
b1111 I
#18600
0!
0.
#18631
1!
1.
b1 H
1G
1%
#18662
0!
0.
#18693
1!
1.
b10 H
#18724
0!
0.
#18755
1!
1.
b11 H
#18786
0!
0.
#18817
1!
1.
b100 H
#18848
0!
0.
#18879
1!
1.
b101 H
#18910
0!
0.
#18941
1!
1.
b110 H
#18972
0!
0.
#19003
1!
1.
b111 H
0G
0%
#19034
0!
0.
#19065
1!
1.
b1000 H
#19096
0!
0.
#19127
1!
1.
b1001 H
#19158
0!
0.
#19189
1!
1.
b1010 H
#19220
0!
0.
#19251
1!
1.
b1011 H
#19282
0!
0.
#19313
1!
1.
b1100 H
#19344
0!
0.
#19375
1!
1.
b1101 H
#19406
0!
0.
#19437
1!
1.
b1110 H
#19468
0!
0.
#19499
1!
1.
b1111 H
#19530
0!
0.
#19561
1!
1.
b10000 H
#19592
0!
0.
#19623
1!
1.
b10001 H
#19654
0!
0.
#19685
1!
1.
b10010 H
#19716
0!
0.
#19747
1!
1.
b10011 H
#19778
0!
0.
#19809
1!
1.
b10100 H
b0 H
b10000 I
#19840
0!
0.
#19871
1!
1.
b1 H
1G
1%
#19902
0!
0.
#19933
1!
1.
b10 H
#19964
0!
0.
#19995
1!
1.
b11 H
#20026
0!
0.
#20057
1!
1.
b100 H
#20088
0!
0.
#20119
1!
1.
b101 H
#20150
0!
0.
#20181
1!
1.
b110 H
#20212
0!
0.
#20243
1!
1.
b111 H
#20274
0!
0.
#20305
1!
1.
b1000 H
#20336
0!
0.
#20367
1!
1.
b1001 H
#20398
0!
0.
#20429
1!
1.
b1010 H
#20460
0!
0.
#20491
1!
1.
b1011 H
#20522
0!
0.
#20553
1!
1.
b1100 H
#20584
0!
0.
#20615
1!
1.
b1101 H
#20646
0!
0.
#20677
1!
1.
b1110 H
0G
0%
#20708
0!
0.
#20739
1!
1.
b1111 H
#20770
0!
0.
#20801
1!
1.
b10000 H
#20832
0!
0.
#20863
1!
1.
b10001 H
#20894
0!
0.
#20925
1!
1.
b10010 H
#20956
0!
0.
#20987
1!
1.
b10011 H
#21018
0!
0.
#21049
1!
1.
b10100 H
b0 H
b10001 I
#21080
0!
0.
#21111
1!
1.
b1 H
1G
1%
#21142
0!
0.
#21173
1!
1.
b10 H
#21204
0!
0.
#21235
1!
1.
b11 H
#21266
0!
0.
#21297
1!
1.
b100 H
#21328
0!
0.
#21359
1!
1.
b101 H
#21390
0!
0.
#21421
1!
1.
b110 H
#21452
0!
0.
#21483
1!
1.
b111 H
0G
0%
#21514
0!
0.
#21545
1!
1.
b1000 H
#21576
0!
0.
#21607
1!
1.
b1001 H
#21638
0!
0.
#21669
1!
1.
b1010 H
#21700
0!
0.
#21731
1!
1.
b1011 H
#21762
0!
0.
#21793
1!
1.
b1100 H
#21824
0!
0.
#21855
1!
1.
b1101 H
#21886
0!
0.
#21917
1!
1.
b1110 H
#21948
0!
0.
#21979
1!
1.
b1111 H
#22010
0!
0.
#22041
1!
1.
b10000 H
#22072
0!
0.
#22103
1!
1.
b10001 H
#22134
0!
0.
#22165
1!
1.
b10010 H
#22196
0!
0.
#22227
1!
1.
b10011 H
#22258
0!
0.
#22289
1!
1.
b10100 H
b0 H
b10010 I
#22320
0!
0.
#22351
1!
1.
b1 H
1G
1%
#22382
0!
0.
#22413
1!
1.
b10 H
#22444
0!
0.
#22475
1!
1.
b11 H
#22506
0!
0.
#22537
1!
1.
b100 H
#22568
0!
0.
#22599
1!
1.
b101 H
#22630
0!
0.
#22661
1!
1.
b110 H
#22692
0!
0.
#22723
1!
1.
b111 H
#22754
0!
0.
#22785
1!
1.
b1000 H
#22816
0!
0.
#22847
1!
1.
b1001 H
#22878
0!
0.
#22909
1!
1.
b1010 H
#22940
0!
0.
#22971
1!
1.
b1011 H
#23002
0!
0.
#23033
1!
1.
b1100 H
#23064
0!
0.
#23095
1!
1.
b1101 H
#23126
0!
0.
#23157
1!
1.
b1110 H
0G
0%
#23188
0!
0.
#23219
1!
1.
b1111 H
#23250
0!
0.
#23281
1!
1.
b10000 H
#23312
0!
0.
#23343
1!
1.
b10001 H
#23374
0!
0.
#23405
1!
1.
b10010 H
#23436
0!
0.
#23467
1!
1.
b10011 H
#23498
0!
0.
#23529
1!
1.
b10100 H
b0 H
b10011 I
#23560
0!
0.
#23591
1!
1.
b1 H
1G
1%
#23622
0!
0.
#23653
1!
1.
b10 H
#23684
0!
0.
#23715
1!
1.
b11 H
#23746
0!
0.
#23777
1!
1.
b100 H
#23808
0!
0.
#23839
1!
1.
b101 H
#23870
0!
0.
#23901
1!
1.
b110 H
#23932
0!
0.
#23963
1!
1.
b111 H
0G
0%
#23994
0!
0.
#24025
1!
1.
b1000 H
#24056
0!
0.
#24087
1!
1.
b1001 H
#24118
0!
0.
#24149
1!
1.
b1010 H
#24180
0!
0.
#24211
1!
1.
b1011 H
#24242
0!
0.
#24273
1!
1.
b1100 H
#24304
0!
0.
#24335
1!
1.
b1101 H
#24366
0!
0.
#24397
1!
1.
b1110 H
#24428
0!
0.
#24459
1!
1.
b1111 H
#24490
0!
0.
#24521
1!
1.
b10000 H
#24552
0!
0.
#24583
1!
1.
b10001 H
#24614
0!
0.
#24645
1!
1.
b10010 H
#24676
0!
0.
#24707
1!
1.
b10011 H
#24738
0!
0.
#24769
1!
1.
b10100 H
b0 H
b10100 I
#24800
0!
0.
#24831
1!
1.
b1 H
1G
1%
#24862
0!
0.
#24893
1!
1.
b10 H
#24924
0!
0.
#24955
1!
1.
b11 H
#24986
0!
0.
#25017
1!
1.
b100 H
#25048
0!
0.
#25079
1!
1.
b101 H
#25110
0!
0.
#25141
1!
1.
b110 H
#25172
0!
0.
#25203
1!
1.
b111 H
#25234
0!
0.
#25265
1!
1.
b1000 H
#25296
0!
0.
#25327
1!
1.
b1001 H
#25358
0!
0.
#25389
1!
1.
b1010 H
#25420
0!
0.
#25451
1!
1.
b1011 H
#25482
0!
0.
#25513
1!
1.
b1100 H
#25544
0!
0.
#25575
1!
1.
b1101 H
#25606
0!
0.
#25637
1!
1.
b1110 H
0G
0%
#25668
0!
0.
#25699
1!
1.
b1111 H
#25730
0!
0.
#25761
1!
1.
b10000 H
#25792
0!
0.
#25823
1!
1.
b10001 H
#25854
0!
0.
#25885
1!
1.
b10010 H
#25916
0!
0.
#25947
1!
1.
b10011 H
#25978
0!
0.
#26009
1!
1.
b10100 H
b0 H
b10101 I
#26040
0!
0.
#26071
1!
1.
b1 H
1G
1%
#26102
0!
0.
#26133
1!
1.
b10 H
#26164
0!
0.
#26195
1!
1.
b11 H
#26226
0!
0.
#26257
1!
1.
b100 H
#26288
0!
0.
#26319
1!
1.
b101 H
#26350
0!
0.
#26381
1!
1.
b110 H
#26412
0!
0.
#26443
1!
1.
b111 H
0G
0%
#26474
0!
0.
#26505
1!
1.
b1000 H
#26536
0!
0.
#26567
1!
1.
b1001 H
#26598
0!
0.
#26629
1!
1.
b1010 H
#26660
0!
0.
#26691
1!
1.
b1011 H
#26722
0!
0.
#26753
1!
1.
b1100 H
#26784
0!
0.
#26815
1!
1.
b1101 H
#26846
0!
0.
#26877
1!
1.
b1110 H
#26908
0!
0.
#26939
1!
1.
b1111 H
#26970
0!
0.
#27001
1!
1.
b10000 H
#27032
0!
0.
#27063
1!
1.
b10001 H
#27094
0!
0.
#27125
1!
1.
b10010 H
#27156
0!
0.
#27187
1!
1.
b10011 H
#27218
0!
0.
#27249
1!
1.
b10100 H
b0 H
b10110 I
#27280
0!
0.
#27311
1!
1.
b1 H
1G
1%
#27342
0!
0.
#27373
1!
1.
b10 H
#27404
0!
0.
#27435
1!
1.
b11 H
#27466
0!
0.
#27497
1!
1.
b100 H
#27528
0!
0.
#27559
1!
1.
b101 H
#27590
0!
0.
#27621
1!
1.
b110 H
#27652
0!
0.
#27683
1!
1.
b111 H
#27714
0!
0.
#27745
1!
1.
b1000 H
#27776
0!
0.
#27807
1!
1.
b1001 H
#27838
0!
0.
#27869
1!
1.
b1010 H
#27900
0!
0.
#27931
1!
1.
b1011 H
#27962
0!
0.
#27993
1!
1.
b1100 H
#28024
0!
0.
#28055
1!
1.
b1101 H
#28086
0!
0.
#28117
1!
1.
b1110 H
0G
0%
#28148
0!
0.
#28179
1!
1.
b1111 H
#28210
0!
0.
#28241
1!
1.
b10000 H
#28272
0!
0.
